gwplot-0.4.1.dist-info/WHEEL
gwplot-0.4.1.dist-info/RECORD
gwplot-0.4.1.dist-info/LICENSE
gwplot-0.4.1.dist-info/METADATA
gwplot.libs/libnss3-77677daf.so
gwplot.libs/libssl3-b5783e6f.so
gwplot.libs/libgw-61b78b94.so
gwplot.libs/libcurl-34c6b10f.so.4.3.0
gwplot.libs/libssl-cd1d6220.so.1.0.2k
gwplot.libs/libhts-cb5337b9.so.1.21
gwplot.libs/libfontconfig-42c558d2.so.1.11.1
gwplot.libs/libsasl2-84219a89.so.3.0.0
gwplot.libs/libEGL-29b68110.so.1.1.0
gwplot.libs/libkrb5support-d0bcff84.so.0.1
gwplot.libs/libpcre-9513aab5.so.1.2.0
gwplot.libs/libssh2-eaeb651a.so.1.0.1
gwplot.libs/libcom_err-2abe824b.so.2.1
gwplot.libs/libnssutil3-3492aa84.so
gwplot.libs/libkeyutils-dfe70bd6.so.1.5
gwplot.libs/libnspr4-4c890ba1.so
gwplot.libs/libfreetype-c0e61f0c.so.6.14.0
gwplot.libs/libkrb5-fcafa220.so.3.3
gwplot.libs/libGLdispatch-dcc1ca97.so.0.0.0
gwplot.libs/libk5crypto-b1f99d5c.so.3.1
gwplot.libs/libGLESv2-3a91e100.so.2.1.0
gwplot.libs/liblzma-004595ca.so.5.2.2
gwplot.libs/libpng15-ce838cd1.so.15.13.0
gwplot.libs/libgssapi_krb5-497db0c6.so.2.2
gwplot.libs/libsmime3-1ce58481.so
gwplot.libs/libbz2-a273e504.so.1.0.6
gwplot.libs/libuuid-f64cda11.so.1.3.0
gwplot.libs/libcrypt-8f974802.so.1
gwplot.libs/libplds4-c4b42550.so
gwplot.libs/libselinux-0922c95c.so.1
gwplot.libs/libcrypto-d3570994.so.1.0.2k
gwplot.libs/libidn-97d26f25.so.11.6.11
gwplot.libs/liblber-2-7eefa761.4.so.2.10.7
gwplot.libs/libldap-2-b8523ca2.4.so.2.10.7
gwplot.libs/libplc4-690d9cce.so
gwplot/glfw_interface.pxd
gwplot/libskia.a
gwplot/__init__.py
gwplot/interface.pxd
gwplot/glfw_interface.cpython-313-x86_64-linux-gnu.so
gwplot/interface.cpython-313-x86_64-linux-gnu.so
gwplot/libgw.so
