Metadata-Version: 2.1
Name: gwplot
Version: 0.4.1
Summary: Visualise genomics data fast
Author-Email: Kez Cleal <clealk@cardiff.ac.uk>
License: MIT License
Classifier: Programming Language :: Python :: 3
Classifier: Operating System :: POSIX :: Linux
Classifier: Operating System :: MacOS :: MacOS X
Project-URL: Repository, https://github.com/kcleal/gwplot
Requires-Python: >=3.9
Requires-Dist: numpy>=1.19.3
Requires-Dist: pysam>=0.23.0
Provides-Extra: test
Requires-Dist: matplotlib; extra == "test"
Requires-Dist: Flask; extra == "test"
Requires-Dist: pillow; extra == "test"
Provides-Extra: pillow
Requires-Dist: pillow; extra == "pillow"
Provides-Extra: all
Requires-Dist: matplotlib; extra == "all"
Requires-Dist: Flask; extra == "all"
Requires-Dist: pillow; extra == "all"
